tKot/__init__.py
tKot/buttons.py
tKot/common.py
tKot/diagram.py
tKot/entries.py
tKot/frames.py
tKot/messagebox.py
tKot/py.typed
tKot/pydantic.py
tKot/settings.py
tkot-0.7.21.dist-info/METADATA
tkot-0.7.21.dist-info/WHEEL
tkot-0.7.21.dist-info/top_level.txt
tkot-0.7.21.dist-info/RECORD
