Metadata-Version: 2.4
Name: tKot
Version: 0.7.21
Author-email: Serj Kotilevski <youserj@outlook.com>
Project-URL: repository, https://github.com/youserj/tkinter_extensions_project
Keywords: tkinter,widget,Pydantic UI
Classifier: Programming Language :: Python :: 3
Classifier: License :: OSI Approved :: MIT License
Classifier: Operating System :: OS Independent
Requires-Python: >=3.11
Requires-Dist: Pillow>=9.4.0
Requires-Dist: numpy>=2.1
Requires-Dist: pydantic>=2.11
Provides-Extra: dev
Requires-Dist: mypy>=1.5.0; extra == "dev"
Requires-Dist: ruff>=0.11; extra == "dev"
Requires-Dist: types-requests; extra == "dev"
Requires-Dist: types-Pillow>=10.2.0; extra == "dev"
